All_In_1/__init__.py
All_In_1/app.py
All_In_1_sathishbilli-0.0.3.dist-info/LICENSE
All_In_1_sathishbilli-0.0.3.dist-info/METADATA
All_In_1_sathishbilli-0.0.3.dist-info/WHEEL
All_In_1_sathishbilli-0.0.3.dist-info/top_level.txt
All_In_1_sathishbilli-0.0.3.dist-info/RECORD
