Metadata-Version: 2.1
Name: All-In-1-sathishbilli
Version: 0.0.3
Summary: this is a basic function for machine learning
Home-page: https://github.com/sathishbilli/All_In_1
Author: sathishbilli
Author-email: sathishmahi398@gmail.com
Project-URL: Bug Tracker, https://github.com/sathishbilli/All_In_1/issues
Classifier: Programming Language :: Python :: 3
Classifier: License :: OSI Approved :: MIT License
Classifier: Operating System :: OS Independent
Requires-Python: >=3.7
License-File: LICENSE
Requires-Dist: matplotlib
Requires-Dist: seaborn
Requires-Dist: numpy
Requires-Dist: pandas
Requires-Dist: statsmodels
Requires-Dist: sklearn
